tailng/__init__.py
tailng/followfile.py
tailng/follownewestfile.py
tailng-2024.8.0.dist-info/METADATA
tailng-2024.8.0.dist-info/WHEEL
tailng-2024.8.0.dist-info/entry_points.txt
tailng-2024.8.0.dist-info/licenses/LICENSE
tailng-2024.8.0.dist-info/RECORD
